Workbook

Sheet Cover
A1: ASIAN PAINTS LIMITED
A3: FINANCIAL ANALYSIS & FORECAST
A5: Historical Performance and Financial Modelling
A8: HISTORICAL PERIOD | D8: FORECAST PERIOD
A9: FY2024 – FY2026 | D9: FY2027E – FY2029E
B12: PROJECT COMPONENTS
B13: Historical Financial Analysis
B14: Revenue & Profitability Forecast
B15: Bear, Base & Bull Scenario Analysis
B16: PAT Sensitivity Analysis
B17: Interactive Financial Dashboard
B20: TOOLS USED
B21: Google Sheets · Microsoft Excel
A23: DISCLAIMER
A24: Illustrative projections based on model assumptions. Not company-issued forecasts.

Sheet Historical Data
A1: Financial Metric | B1: FY24 | C1: FY25 | D1: FY26 | E1: Unit
A2: Revenue | B2: 31227 | C2: 29552.65 | D2: 30769.48 | E2: ₹Cr
A3: Other Income | B3: 821.92 | C3: 770.31 | D3: 932.66 | E3: ₹Cr
A4: Revenue Growth | B4: ="-" -> - | C4: =(C2/B2)-1 -> -0.053618663 | D4: =(D2/C2)-1 -> 0.041174988 | E4: %
A5: Cost of Materials | B5: 17471.89 | C5: 16791.84 | D5: 17067.72 | E5: ₹Cr
A6: Employee Expenses | B6: 1816.19 | C6: 2013.58 | D6: 2176.68 | E6: ₹Cr
A7: Other Operating Expenses | B7: 4895.08 | C7: 5190.69 | D7: 5344.61 | E7: ₹Cr
A8: EBITDA | B8: 7865.74 | C8: 6326.85 | D8: 7113.13 | E8: ₹Cr
A9: EBITDA Margin | B9: =B8/B2 -> 0.25188907 | C9: =C8/C2 -> 0.2140874 | D9: =D8/D2 -> 0.23117485 | E9: %
A10: Depreciation & Amortisation | B10: 742.93 | C10: 901.85 | D10: 1085.65 | E10: ₹Cr
A11: EBIT | B11: =B8-B10 -> 7122.81 | C11: =C8-C10 -> 5425 | D11: =D8-D10 -> 6027.48 | E11: ₹Cr
A12: Finance Costs | B12: 124.09 | C12: 143.77 | D12: 127.35 | E12: ₹Cr
A13: Profit Before Tax | B13: 6998.72 | C13: 4901.6 | D13: 5733.6 | E13: ₹Cr
A14: Exceptional Items | B14: 0 | C14: 379.63 | D14: 166.53 | E14: ₹Cr
A15: Tax Expense | B15: 1683.71 | C15: 1313.53 | D15: 1489.43 | E15: ₹Cr
A16: Profit After Tax | B16: 5315.01 | C16: 3588.07 | D16: 4244.17 | E16: ₹Cr
A17: PAT Margin | B17: =B16/B2 -> 0.17020559 | C17: =C16/C2 -> 0.1214128 | D17: =D16/D2 -> 0.13793441 | E17: %
A18: EPS | B18: 55.43 | C18: 37.43 | D18: 44.27 | E18: ₹
A19: Source | B19: Asian Paints Integrated Annual Report FY2024-25 — Standalone financials (FY24) | C19: Asian Paints Integrated Annual Report FY2024-25 — Standalone financials (FY25) | D19: Asian Paints Integrated Annual Report FY2025-26 — Standalone financials (FY26)
A21: D&A % of Revenue | B21: =B10/B2 -> 0.02379127 | C21: =C10/C2 -> 0.030516722 | D21: =D10/D2 -> 0.035283339 | E21: %
A22: Finance cost % of revenue | B22: =B12/B2 -> 0.0039738047 | C22: =C12/C2 -> 0.0048648768 | D22: =D12/D2 -> 0.0041388415 | E22: %
A23: Effective tax rate | B23: =B15/B13 -> 0.24057399 | C23: =C15/C13 -> 0.26797984 | D23: =D15/D13 -> 0.25977222 | E23: %

Sheet Assumptions
A1: Assumption | B1: Bear | C1: Base | D1: Bull
A2: Revenue Growth | B2: -0.03 | C2: =AVERAGE('Historical Data'!C4:D4) -> -0.0062218378 | D2: 0.08
A3: EBITDA Margin | B3: 0.19 | C3: =AVERAGE('Historical Data'!C9:D9) -> 0.22263113 | D3: 0.25
A4: D&A % of Revenue | B4: 0.04 | C4: =AVERAGE('Historical Data'!C21:D21) -> 0.032900031 | D4: 0.03
A5: Finance Cost % | B5: 0.007 | C5: =AVERAGE('Historical Data'!C22:D22) -> 0.0045018591 | D5: 0.003
A6: Tax Rate | B6: 0.28 | C6: =AVERAGE('Historical Data'!C23:D23) -> 0.26387603 | D6: 0.25
A8: ASSUMPTION METHODOLOGY
A9: Base Case assumptions use the average of FY25 and FY26 historical ratios.
A10: Bear Case represents a conservative operating environment.
A11: Bull Case represents stronger revenue growth and profitability.
A12: All scenarios are illustrative and do not represent company guidance.

Sheet Forecast Model
A1: Selected scenario | B1: Bull
A3: Revenue Growth | B3: {=INDEX(Assumptions!$B$2:$D$2,1,MATCH($B$1,Assumptions!$B$1:$D$1,0))} -> 0.08
A4: EBITDA Margin | B4: {=INDEX(Assumptions!$B$3:$D$3,1,MATCH($B$1,Assumptions!$B$1:$D$1,0))} -> 0.25
A5: D&A % of Revenue | B5: {=INDEX(Assumptions!$B$4:$D$4,1,MATCH($B$1,Assumptions!$B$1:$D$1,0))} -> 0.03
A6: Finance Cost % | B6: {=INDEX(Assumptions!$B$5:$D$5,1,MATCH($B$1,Assumptions!$B$1:$D$1,0))} -> 0.003
A7: Tax Rate | B7: {=INDEX(Assumptions!$B$6:$D$6,1,MATCH($B$1,Assumptions!$B$1:$D$1,0))} -> 0.25
A10: Financial Metric | B10: FY26 Actual | C10: FY27E | D10: FY28E | E10: FY29E
A11: Revenue | B11: ='Historical Data'!D2 -> 30769.48 | C11: =B11*(1+$B$3) -> 33231.038 | D11: =C11*(1+$B$3) -> 35889.521 | E11: =D11*(1+$B$3) -> 38760.683
A12: Revenue Growth | B12: ='Historical Data'!D4 -> 0.041174988 | C12: =C11/B11-1 -> 0.08 | D12: =D11/C11-1 -> 0.08 | E12: =E11/D11-1 -> 0.08
A13: EBITDA | B13: ='Historical Data'!D8 -> 7113.13 | C13: =C11*$B$4 -> 8307.7596 | D13: =D11*$B$4 -> 8972.3804 | E13: =E11*$B$4 -> 9690.1708
A14: EBITDA Margin | B14: ='Historical Data'!D9 -> 0.23117485 | C14: =C13/C11 -> 0.25 | D14: =D13/D11 -> 0.25 | E14: =E13/E11 -> 0.25
A15: D&A | B15: ='Historical Data'!D10 -> 1085.65 | C15: =C11*$B$5 -> 996.93115 | D15: =D11*$B$5 -> 1076.6856 | E15: =E11*$B$5 -> 1162.8205
A16: EBIT | B16: ='Historical Data'!D11 -> 6027.48 | C16: =C13-C15 -> 7310.8284 | D16: =D13-D15 -> 7895.6947 | E16: =E13-E15 -> 8527.3503
A17: Finance Costs | B17: ='Historical Data'!D12 -> 127.35 | C17: =C11*$B$6 -> 99.693115 | D17: =D11*$B$6 -> 107.66856 | E17: =E11*$B$6 -> 116.28205
A18: Exceptional Items | B18: ='Historical Data'!D14 -> 166.53 | C18: =0 -> 0 | D18: =0 -> 0 | E18: =0 -> 0
A19: Profit Before Tax | B19: ='Historical Data'!D13 -> 5733.6 | C19: =C16-C17-C18 -> 7211.1353 | D19: =D16-D17-D18 -> 7788.0262 | E19: =E16-E17-E18 -> 8411.0683
A20: Tax Expense | B20: ='Historical Data'!D15 -> 1489.43 | C20: =C19*$B$7 -> 1802.7838 | D20: =D19*$B$7 -> 1947.0065 | E20: =E19*$B$7 -> 2102.7671
A21: Profit After Tax | B21: ='Historical Data'!D16 -> 4244.17 | C21: =C19-C20 -> 5408.3515 | D21: =D19-D20 -> 5841.0196 | E21: =E19-E20 -> 6308.3012
A22: PAT Margin | B22: ='Historical Data'!D17 -> 0.13793441 | C22: =C21/C11 -> 0.16275 | D22: =D21/D11 -> 0.16275 | E22: =E21/E11 -> 0.16275

Sheet Financial Statements
A1: Financial Metric | B1: FY24 Actual | C1: FY25 Actual | D1: FY26 Actual | E1: FY27E | F1: FY28E | G1: FY29E
A2: Revenue | B2: ='Historical Data'!B2 -> 31227 | C2: ='Historical Data'!C2 -> 29552.65 | D2: ='Historical Data'!D2 -> 30769.48 | E2: ='Forecast Model'!C11 -> 33231.038 | F2: ='Forecast Model'!D11 -> 35889.521 | G2: ='Forecast Model'!E11 -> 38760.683
A3: Revenue Growth | B3: ='Historical Data'!B4 -> - | C3: ='Historical Data'!C4 -> -0.053618663 | D3: ='Historical Data'!D4 -> 0.041174988 | E3: ='Forecast Model'!C12 -> 0.08 | F3: ='Forecast Model'!D12 -> 0.08 | G3: ='Forecast Model'!E12 -> 0.08
A4: EBITDA | B4: ='Historical Data'!B8 -> 7865.74 | C4: ='Historical Data'!C8 -> 6326.85 | D4: ='Historical Data'!D8 -> 7113.13 | E4: ='Forecast Model'!C13 -> 8307.7596 | F4: ='Forecast Model'!D13 -> 8972.3804 | G4: ='Forecast Model'!E13 -> 9690.1708
A5: EBITDA Margin | B5: ='Historical Data'!B9 -> 0.25188907 | C5: ='Historical Data'!C9 -> 0.2140874 | D5: ='Historical Data'!D9 -> 0.23117485 | E5: ='Forecast Model'!C14 -> 0.25 | F5: ='Forecast Model'!D14 -> 0.25 | G5: ='Forecast Model'!E14 -> 0.25
A6: Depreciation & Amortisation | B6: ='Historical Data'!B10 -> 742.93 | C6: ='Historical Data'!C10 -> 901.85 | D6: ='Historical Data'!D10 -> 1085.65 | E6: ='Forecast Model'!C15 -> 996.93115 | F6: ='Forecast Model'!D15 -> 1076.6856 | G6: ='Forecast Model'!E15 -> 1162.8205
A7: EBIT | B7: ='Historical Data'!B11 -> 7122.81 | C7: ='Historical Data'!C11 -> 5425 | D7: ='Historical Data'!D11 -> 6027.48 | E7: ='Forecast Model'!C16 -> 7310.8284 | F7: ='Forecast Model'!D16 -> 7895.6947 | G7: ='Forecast Model'!E16 -> 8527.3503
A8: Finance Costs | B8: ='Historical Data'!B12 -> 124.09 | C8: ='Historical Data'!C12 -> 143.77 | D8: ='Historical Data'!D12 -> 127.35 | E8: ='Forecast Model'!C17 -> 99.693115 | F8: ='Forecast Model'!D17 -> 107.66856 | G8: ='Forecast Model'!E17 -> 116.28205
A9: Exceptional Items | B9: ='Historical Data'!B14 -> 0 | C9: ='Historical Data'!C14 -> 379.63 | D9: ='Historical Data'!D14 -> 166.53 | E9: ='Forecast Model'!C18 -> 0 | F9: ='Forecast Model'!D18 -> 0 | G9: ='Forecast Model'!E18 -> 0
A10: Profit Before Tax | B10: ='Historical Data'!B13 -> 6998.72 | C10: ='Historical Data'!C13 -> 4901.6 | D10: ='Historical Data'!D13 -> 5733.6 | E10: ='Forecast Model'!C19 -> 7211.1353 | F10: ='Forecast Model'!D19 -> 7788.0262 | G10: ='Forecast Model'!E19 -> 8411.0683
A11: Tax Expense | B11: ='Historical Data'!B15 -> 1683.71 | C11: ='Historical Data'!C15 -> 1313.53 | D11: ='Historical Data'!D15 -> 1489.43 | E11: ='Forecast Model'!C20 -> 1802.7838 | F11: ='Forecast Model'!D20 -> 1947.0065 | G11: ='Forecast Model'!E20 -> 2102.7671
A12: Profit After Tax | B12: ='Historical Data'!B16 -> 5315.01 | C12: ='Historical Data'!C16 -> 3588.07 | D12: ='Historical Data'!D16 -> 4244.17 | E12: ='Forecast Model'!C21 -> 5408.3515 | F12: ='Forecast Model'!D21 -> 5841.0196 | G12: ='Forecast Model'!E21 -> 6308.3012
A13: PAT Margin | B13: ='Historical Data'!B17 -> 0.17020559 | C13: ='Historical Data'!C17 -> 0.1214128 | D13: ='Historical Data'!D17 -> 0.13793441 | E13: ='Forecast Model'!C22 -> 0.16275 | F13: ='Forecast Model'!D22 -> 0.16275 | G13: ='Forecast Model'!E22 -> 0.16275

Sheet Scenario Analysis
A1: FY29 Scenario Analysis
A3: Financial Metric | B3: Bear | C3: Base | D3: Bull
A4: Revenue | B4: ='Historical Data'!D2*(1+Assumptions!B2)^3 -> 28082.474 | C4: ='Historical Data'!D2*(1+Assumptions!C2)^3 -> 30198.718 | D4: ='Historical Data'!D2*(1+Assumptions!D2)^3 -> 38760.683
A5: EBITDA | B5: =B4*Assumptions!B3 -> 5335.67 | C5: =C4*Assumptions!C3 -> 6723.1746 | D5: =D4*Assumptions!D3 -> 9690.1708
A6: EBITDA Margin | B6: =B5/B4 -> 0.19 | C6: =C5/C4 -> 0.22263113 | D6: =D5/D4 -> 0.25
A7: Profit Before Tax | B7: =B5-(B4*Assumptions!B4)-(B4*Assumptions!B5) -> 4015.7937 | C7: =C5-(C4*Assumptions!C4)-(C4*Assumptions!C5) -> 5593.6854 | D7: =D5-(D4*Assumptions!D4)-(D4*Assumptions!D5) -> 8411.0683
A8: Profit After Tax | B8: =B7*(1-Assumptions!B6) -> 2891.3715 | C8: =C7*(1-Assumptions!C6) -> 4117.6459 | D8: =D7*(1-Assumptions!D6) -> 6308.3012
A9: PAT Margin | B9: =B8/B4 -> 0.10296 | C9: =C8/C4 -> 0.13635168 | D9: =D8/D4 -> 0.16275
A11: Illustrative scenarios; not company-issued forecasts. Amounts in ₹ crore.

Sheet Sensitivity
A1: FY29 PAT Sensitivity Analysis
A3: Revenue Growth / EBITDA Margin | B3: 0.2 | C3: 0.2226 | D3: 0.25
A4: -0.03 | B4: =('Historical Data'!$D$2*(1+$A4)^3)*(B$3-Assumptions!$C$4-Assumptions!$C$5)*(1-Assumptions!$C$6) -> 3361.2577 | C4: =('Historical Data'!$D$2*(1+$A4)^3)*(C$3-Assumptions!$C$4-Assumptions!$C$5)*(1-Assumptions!$C$6) -> 3828.449 | D4: =('Historical Data'!$D$2*(1+$A4)^3)*(D$3-Assumptions!$C$4-Assumptions!$C$5)*(1-Assumptions!$C$6) -> 4394.8668
A5: 0 | B5: =('Historical Data'!$D$2*(1+$A5)^3)*(B$3-Assumptions!$C$4-Assumptions!$C$5)*(1-Assumptions!$C$6) -> 3682.8719 | C5: =('Historical Data'!$D$2*(1+$A5)^3)*(C$3-Assumptions!$C$4-Assumptions!$C$5)*(1-Assumptions!$C$6) -> 4194.7653 | D5: =('Historical Data'!$D$2*(1+$A5)^3)*(D$3-Assumptions!$C$4-Assumptions!$C$5)*(1-Assumptions!$C$6) -> 4815.3795
A6: 0.04 | B6: =('Historical Data'!$D$2*(1+$A6)^3)*(B$3-Assumptions!$C$4-Assumptions!$C$5)*(1-Assumptions!$C$6) -> 4142.73 | C6: =('Historical Data'!$D$2*(1+$A6)^3)*(C$3-Assumptions!$C$4-Assumptions!$C$5)*(1-Assumptions!$C$6) -> 4718.5405 | D6: =('Historical Data'!$D$2*(1+$A6)^3)*(D$3-Assumptions!$C$4-Assumptions!$C$5)*(1-Assumptions!$C$6) -> 5416.647
A7: 0.08 | B7: =('Historical Data'!$D$2*(1+$A7)^3)*(B$3-Assumptions!$C$4-Assumptions!$C$5)*(1-Assumptions!$C$6) -> 4639.3579 | C7: =('Historical Data'!$D$2*(1+$A7)^3)*(C$3-Assumptions!$C$4-Assumptions!$C$5)*(1-Assumptions!$C$6) -> 5284.1962 | D7: =('Historical Data'!$D$2*(1+$A7)^3)*(D$3-Assumptions!$C$4-Assumptions!$C$5)*(1-Assumptions!$C$6) -> 6065.9913
A9: Illustrative FY29 PAT; Base Case D&A, finance cost and tax assumptions held constant.

Sheet Dashboard
A1: ASIAN PAINTS — FINANCIAL ANALYSIS | M1: Financial Year | N1: Revenue (₹ Cr)
A2: Historical Performance & Forecast · FY24–FY29 | M2: FY24 | N2: ='Financial Statements'!B2 -> 31227
A3: ="Historical Performance & Forecast · FY24–FY29 · Current Scenario: "&'Forecast Model'!B1 -> Historical Performance & Forecast · FY24–FY29 · Current Scenario: Bull | M3: FY25 | N3: ='Financial Statements'!C2 -> 29552.65
A4: KEY FINANCIAL INDICATORS | M4: FY26 | N4: ='Financial Statements'!D2 -> 30769.48
A5: FY26 Revenue | C5: FY26 EBITDA | E5: FY26 PAT | G5: FY26 EBITDA Margin | I5: FY29 Revenue | K5: FY29 PAT | M5: FY27E | N5: ='Financial Statements'!E2 -> 33231.038
A6: ='Financial Statements'!D2 -> 30769.48 | C6: ='Financial Statements'!D4 -> 7113.13 | E6: ='Financial Statements'!D12 -> 4244.17 | G6: ='Financial Statements'!D5 -> 0.23117485 | I6: ='Financial Statements'!G2 -> 38760.683 | K6: ='Financial Statements'!G12 -> 6308.3012 | M6: FY28E | N6: ='Financial Statements'!F2 -> 35889.521
M7: FY29E | N7: ='Financial Statements'!G2 -> 38760.683
A8: HISTORICAL & FORECAST TRENDS
M9: Financial Year | N9: EBITDA Margin | O9: PAT Margin
M10: FY24 | N10: ='Financial Statements'!B5 -> 0.25188907 | O10: ='Financial Statements'!B13 -> 0.17020559
M11: FY25 | N11: ='Financial Statements'!C5 -> 0.2140874 | O11: ='Financial Statements'!C13 -> 0.1214128
M12: FY26 | N12: ='Financial Statements'!D5 -> 0.23117485 | O12: ='Financial Statements'!D13 -> 0.13793441
M13: FY27E | N13: ='Financial Statements'!E5 -> 0.25 | O13: ='Financial Statements'!E13 -> 0.16275
M14: FY28E | N14: ='Financial Statements'!F5 -> 0.25 | O14: ='Financial Statements'!F13 -> 0.16275
M15: FY29E | N15: ='Financial Statements'!G5 -> 0.25 | O15: ='Financial Statements'!G13 -> 0.16275
A20: SCENARIO COMPARISON
A21: Metric | B21: Bear | C21: Base | D21: Bull
A22: FY29 Revenue | B22: ='Scenario Analysis'!B4 -> 28082.474 | C22: ='Scenario Analysis'!C4 -> 30198.718 | D22: ='Scenario Analysis'!D4 -> 38760.683
A23: FY29 EBITDA | B23: ='Scenario Analysis'!B5 -> 5335.67 | C23: ='Scenario Analysis'!C5 -> 6723.1746 | D23: ='Scenario Analysis'!D5 -> 9690.1708
A24: FY29 PAT | B24: ='Scenario Analysis'!B8 -> 2891.3715 | C24: ='Scenario Analysis'!C8 -> 4117.6459 | D24: ='Scenario Analysis'!D8 -> 6308.3012
A25: FY29 PAT Margin | B25: ='Scenario Analysis'!B9 -> 0.10296 | C25: ='Scenario Analysis'!C9 -> 0.13635168 | D25: ='Scenario Analysis'!D9 -> 0.16275
A27: KEY OBSERVATIONS
A28: FY25 revenue declined before recovering in FY26.
A29: The Bull scenario delivers the highest projected FY29 revenue and PAT.
A30: Forecast outcomes depend on revenue growth, EBITDA margin and other assumptions.

Sheet Analysis Notes
A1: ASIAN PAINTS — FINANCIAL ANALYSIS
A3: 1. Historical Performance
A4: Revenue declined in FY25 before recovering in FY26.
A5: EBITDA margin declined in FY25 and recovered in FY26.
A7: 2. Forecast Assumptions
A8: Revenue growth, EBITDA margin, D&A, finance costs and tax rate drive the forecasts.
A9: Bear, Base and Bull scenarios represent illustrative assumptions, not official company guidance.
A11: 3. Scenario Analysis
A12: The Bull case produces the highest projected FY29 revenue and PAT under the selected assumptions.
A14: 4. Sensitivity Analysis
A15: FY29 PAT changes with revenue growth and EBITDA margin, while Base Case D&A, finance costs and tax assumptions remain constant.
A17: 5. Key Risks and Limitations
... A20: Forecast EBITDA is estimated by applying the assumed EBITDA margin to revenue. Other income is not forecast separately, so projected results may differ from the company's reported EBITDA methodology.
